switchboard_tg2
