Metadata-Version: 1.0
Name: switchboard-tg2
Version: 0.3
Summary: UNKNOWN
Home-page: http://sf.net/projects/switchboard-tg2
Author: Kyle Adams
Author-email: kadams54@users.sourceforge.net
License: UNKNOWN
Keywords: turbogears2.application
Platform: UNKNOWN
